stc_geck/__init__.py
stc_geck/advices.py
stc_geck/cli.py
stc_geck/client.py
stc_geck/exceptions.py
stc_geck/utils.py
stc_geck-1.8.48.dist-info/METADATA
stc_geck-1.8.48.dist-info/WHEEL
stc_geck-1.8.48.dist-info/entry_points.txt
stc_geck-1.8.48.dist-info/RECORD
