Metadata-Version: 2.1
Name: stc-geck
Version: 1.8.48
Summary: GECK (Garden Of Eden Creation Kit) is a toolkit for setting up and maintaning STC
Author: Interdimensional Walker
Classifier: Programming Language :: Python :: 2
Classifier: Programming Language :: Python :: 2.7
Classifier: Programming Language :: Python :: 3
Classifier: Programming Language :: Python :: 3.4
Classifier: Programming Language :: Python :: 3.5
Classifier: Programming Language :: Python :: 3.6
Classifier: Programming Language :: Python :: 3.7
Classifier: Programming Language :: Python :: 3.8
Classifier: Programming Language :: Python :: 3.9
Classifier: Programming Language :: Python :: 3.10
Classifier: Programming Language :: Python :: 3.11
Classifier: Programming Language :: Python :: 3.12
Requires-Dist: aiohttp (>=3.9,<3.10)
Requires-Dist: aiokit (>=1.3,<1.4)
Requires-Dist: aiosumma (>=2.47.1,<2.48.0)
Requires-Dist: fire (>=0.5.0,<0.6.0)
Requires-Dist: humanfriendly (>=10.0,<10.1)
Requires-Dist: ipfs-hamt-directory-py (>=0.1.1,<0.2.0)
Requires-Dist: izihawa-ipfs-api (>=1.0.7,<1.1.0)
Requires-Dist: izihawa-utils (>=1.2,<1.3)
Requires-Dist: multidict (>=6.0.4,<6.1.0)
Requires-Dist: summa-embed (>=0.23.0,<0.24.0)
Requires-Dist: termcolor (>=2.3.0,<2.4.0)
